Adafruit_SSD1306/__init__.py
Adafruit_SSD1306/SSD1306.py
Adafruit_SSD1306-1.6.1.dist-info/metadata.json
Adafruit_SSD1306-1.6.1.dist-info/METADATA
Adafruit_SSD1306-1.6.1.dist-info/RECORD
Adafruit_SSD1306-1.6.1.dist-info/WHEEL
Adafruit_SSD1306-1.6.1.dist-info/DESCRIPTION.rst
Adafruit_SSD1306-1.6.1.dist-info/dependency_links.txt
Adafruit_SSD1306-1.6.1.dist-info/top_level.txt
